[
  {
    "full_name": "vendure-ecommerce/vendure",
    "stargazers_count": 3779,
    "open_issues_count": 210,
    "forks_count": 644
  },
  {
    "full_name": "vercel/next.js",
    "stargazers_count": 93011,
    "open_issues_count": 1390,
    "forks_count": 20376
  },
  {
    "full_name": "remix-run/remix",
    "stargazers_count": 19327,
    "open_issues_count": 313,
    "forks_count": 1558
  },
  {
    "full_name": "solidjs/solid",
    "stargazers_count": 22259,
    "open_issues_count": 20,
    "forks_count": 572
  },
  {
    "full_name": "facebook/react",
    "stargazers_count": 195189,
    "open_issues_count": 1107,
    "forks_count": 40386
  },
  {
    "full_name": "open-sauced/open-sauced",
    "stargazers_count": 788,
    "open_issues_count": 22,
    "forks_count": 389
  }
]