[
  {
    "full_name": "vendure-ecommerce/vendure",
    "stargazers_count": 6219,
    "open_issues_count": 469,
    "forks_count": 1121
  },
  {
    "full_name": "vercel/next.js",
    "stargazers_count": 131827,
    "open_issues_count": 3213,
    "forks_count": 28376
  },
  {
    "full_name": "remix-run/remix",
    "stargazers_count": 31230,
    "open_issues_count": 174,
    "forks_count": 2636
  },
  {
    "full_name": "solidjs/solid",
    "stargazers_count": 33591,
    "open_issues_count": 125,
    "forks_count": 966
  },
  {
    "full_name": "facebook/react",
    "stargazers_count": 235442,
    "open_issues_count": 1046,
    "forks_count": 48490
  },
  {
    "full_name": "open-sauced/open-sauced",
    "stargazers_count": 951,
    "open_issues_count": 0,
    "forks_count": 1117
  }
]