[
  {
    "full_name": "dudykr/stc",
    "stargazers_count": 2421,
    "open_issues_count": 26,
    "forks_count": 62
  },
  {
    "full_name": "marcj/TypeRunner",
    "stargazers_count": 2298,
    "open_issues_count": 3,
    "forks_count": 33
  },
  {
    "full_name": "penpot/penpot",
    "stargazers_count": 19110,
    "open_issues_count": 230,
    "forks_count": 861
  },
  {
    "full_name": "juliendecharentenay/yew-investigation",
    "stargazers_count": 1,
    "open_issues_count": 0,
    "forks_count": 0
  },
  {
    "full_name": "Sygil-Dev/sygil-webui",
    "stargazers_count": 5620,
    "open_issues_count": 48,
    "forks_count": 647
  },
  {
    "full_name": "facebook/react",
    "stargazers_count": 197206,
    "open_issues_count": 1063,
    "forks_count": 40887
  },
  {
    "full_name": "upscayl/upscayl",
    "stargazers_count": 5938,
    "open_issues_count": 26,
    "forks_count": 138
  },
  {
    "full_name": "redwoodjs/redwood",
    "stargazers_count": 15068,
    "open_issues_count": 416,
    "forks_count": 812
  },
  {
    "full_name": "aidenybai/million",
    "stargazers_count": 5350,
    "open_issues_count": 11,
    "forks_count": 148
  },
  {
    "full_name": "ahmedyounis1st/Machine-Learning-Road-Map",
    "stargazers_count": 38,
    "open_issues_count": 0,
    "forks_count": 3
  },
  {
    "full_name": "reactwg/react-18",
    "stargazers_count": 4785,
    "open_issues_count": 0,
    "forks_count": 128
  },
  {
    "full_name": "ahmed-bermawy/laravel-dashboard",
    "stargazers_count": 8,
    "open_issues_count": 0,
    "forks_count": 3
  },
  {
    "full_name": "formkit/auto-animate",
    "stargazers_count": 6052,
    "open_issues_count": 42,
    "forks_count": 103
  },
  {
    "full_name": "dprint/dprint",
    "stargazers_count": 1601,
    "open_issues_count": 43,
    "forks_count": 34
  },
  {
    "full_name": "rome/tools",
    "stargazers_count": 19595,
    "open_issues_count": 77,
    "forks_count": 600
  },
  {
    "full_name": "tauri-apps/tauri",
    "stargazers_count": 53573,
    "open_issues_count": 257,
    "forks_count": 1369
  },
  {
    "full_name": "maplibre/maplibre-rs",
    "stargazers_count": 904,
    "open_issues_count": 63,
    "forks_count": 49
  },
  {
    "full_name": "mgechev/mk.js",
    "stargazers_count": 1447,
    "open_issues_count": 0,
    "forks_count": 394
  },
  {
    "full_name": "francoismassart/eslint-plugin-tailwindcss",
    "stargazers_count": 541,
    "open_issues_count": 22,
    "forks_count": 29
  },
  {
    "full_name": "caiogondim/fast-memoize.js",
    "stargazers_count": 2525,
    "open_issues_count": 24,
    "forks_count": 107
  },
  {
    "full_name": "RapidAPI/DevRel-Examples-External",
    "stargazers_count": 250,
    "open_issues_count": 1,
    "forks_count": 58
  },
  {
    "full_name": "trpc/trpc",
    "stargazers_count": 14791,
    "open_issues_count": 75,
    "forks_count": 465
  },
  {
    "full_name": "argyleink/gui-challenges",
    "stargazers_count": 1924,
    "open_issues_count": 14,
    "forks_count": 248
  },
  {
    "full_name": "wg/wrk",
    "stargazers_count": 33205,
    "open_issues_count": 172,
    "forks_count": 2746
  },
  {
    "full_name": "digitalocean/Kubernetes-Starter-Kit-Developers",
    "stargazers_count": 460,
    "open_issues_count": 14,
    "forks_count": 165
  },
  {
    "full_name": "tkssharma/nestjs-advance-course",
    "stargazers_count": 168,
    "open_issues_count": 1,
    "forks_count": 94
  },
  {
    "full_name": "DefinitelyTyped/DefinitelyTyped",
    "stargazers_count": 41442,
    "open_issues_count": 914,
    "forks_count": 28231
  },
  {
    "full_name": "bvaughn/react-window",
    "stargazers_count": 13251,
    "open_issues_count": 200,
    "forks_count": 736
  },
  {
    "full_name": "welldone-software/why-did-you-render",
    "stargazers_count": 9350,
    "open_issues_count": 24,
    "forks_count": 168
  },
  {
    "full_name": "mgechev/javascript-algorithms",
    "stargazers_count": 7544,
    "open_issues_count": 9,
    "forks_count": 1297
  }
]